{
  "changelogDate": "20220521085246",
  "dto": "mapstruct",
  "fields": [
    {
      "fieldName": "title",
      "fieldType": "String"
    },
    {
      "fieldName": "description",
      "fieldType": "String"
    },
    {
      "fieldName": "publicationDate",
      "fieldType": "LocalDate"
    },
    {
      "fieldName": "price",
      "fieldType": "BigDecimal"
    }
  ],
  "jpaMetamodelFiltering": true,
  "name": "Book",
  "pagination": "pagination",
  "readOnly": false,
  "relationships": [
    {
      "otherEntityField": "name",
      "otherEntityName": "author",
      "relationshipName": "authorBook",
      "relationshipType": "many-to-one"
    }
  ],
  "service": "serviceImpl"
}
